constallation_mmr/__init__.py
constallation_mmr/rig.py
constallation_mmr/riggroup.py
constallation_mmr-1.1.0.dist-info/LICENSE
constallation_mmr-1.1.0.dist-info/METADATA
constallation_mmr-1.1.0.dist-info/WHEEL
constallation_mmr-1.1.0.dist-info/RECORD
