Metadata-Version: 2.1
Name: constallation-mmr
Version: 1.1.0
Summary: An OOP-heavy wrapper for the Mining Rig Rentals API
Author: CoulterStutz
Author-email: coultercash@gmail.com
Requires-Python: >=3.9
Classifier: Programming Language :: Python :: 3
Classifier: Programming Language :: Python :: 3.9
Classifier: Programming Language :: Python :: 3.10
Classifier: Programming Language :: Python :: 3.11
Classifier: Programming Language :: Python :: 3.12
Requires-Dist: requests (>=2.32.3)
